PokedexWal2/__init__.py
PokedexWal2/pokemon.csv
PokedexWal2/random_pokemon.py
PokedexWal2-1.0.0.dist-info/METADATA
PokedexWal2-1.0.0.dist-info/WHEEL
PokedexWal2-1.0.0.dist-info/top_level.txt
PokedexWal2-1.0.0.dist-info/RECORD
